libkplug/__init__.py
libksettings/__init__.py
libkplug-0.3.0.dist-info/LICENSE
libkplug-0.3.0.dist-info/METADATA
libkplug-0.3.0.dist-info/WHEEL
libkplug-0.3.0.dist-info/top_level.txt
libkplug-0.3.0.dist-info/RECORD
