Metadata-Version: 2.1
Name: libkplug
Version: 0.3.0
Summary: Plugin Framework
Home-page: https://github.com/unixunion/libkplug/
Author: Kegan Holtzhausen
Author-email: marzubus@gmail.com
License: UNKNOWN
Platform: UNKNOWN
Requires-Dist: PyYAML (>=3.11)
